jelka/__init__.py
jelka/jelka.py
jelka/py.typed
jelka/util.py
jelka/shapes/__init__.py
jelka/shapes/path.py
jelka/shapes/plane.py
jelka/shapes/shape.py
jelka/shapes/sphere.py
jelka/types/__init__.py
jelka/types/aabb.py
jelka/types/color.py
jelka/types/position.py
jelka-0.0.9.dist-info/METADATA
jelka-0.0.9.dist-info/WHEEL
jelka-0.0.9.dist-info/licenses/LICENSE
jelka-0.0.9.dist-info/RECORD
