Metadata-Version: 2.4
Name: jelka
Version: 0.0.9
Summary: Python API for Jelka FMF patterns
Project-URL: Homepage, https://github.com/Jelka-FMF/JelkaPy
Project-URL: Issues, https://github.com/Jelka-FMF/JelkaPy/issues
Author-email: Bor Brudar <bor.brudar@gmail.com>, Filip Štamcar <projects@filips.si>
License-File: LICENSE
Classifier: Development Status :: 5 - Production/Stable
Classifier: License :: OSI Approved :: MIT License
Classifier: Operating System :: OS Independent
Classifier: Programming Language :: Python :: 3
Classifier: Typing :: Typed
Requires-Python: >=3.8
Requires-Dist: jelka-validator
